{
  "image_path": "car/scene1/surface_damage/0106.jpg",
  "coordinates": "[(524,656),(561,668)]",
  "type": "surface damage",
  "conversation": {
    "Question": "Which of the following options correctly identifies the defects in the image?\n(A)no defect(B)fading(C)crack(D)surface damage(E)dent.",
    "options": {
      "A": "no defect",
      "B": "fading",
      "C": "crack",
      "D": "surface damage",
      "E": "dent"
    },
    "Reasoning": "My analysis based on this image is as follows:There is no evidence of fading as the color gradient is consistent across the hood. There is no crack present as the surface integrity is maintained without any visible separation or break in the material. There is no dent as the contour of the hood remains smooth without any inward deformation. The image shows a scratch on the car's hood near the headlight which is a form of surface damage. The anomaly region coordinates [[(524,656),(561,668)]] and the defect type is surface damage. Likely cause: Minor abrasion from contact with a rough object. The answer is (D).",
    "Answer": "(D)surface damage"
  }
}